djangocms_pai_material_components_web/__init__.py
djangocms_pai_material_components_web/admin.py
djangocms_pai_material_components_web/apps.py
djangocms_pai_material_components_web/skeleton.py
djangocms_pai_material_components_web/migrations/__init__.py
djangocms_pai_material_components_web/static/djangocms_pai_material_components_web/package-lock.json
djangocms_pai_material_components_web/static/djangocms_pai_material_components_web/package.json
djangocms_pai_material_components_web/static/djangocms_pai_material_components_web/node_modules/@material/animation/README.md
djangocms_pai_material_components_web/static/djangocms_pai_material_components_web/node_modules/@material/animation/_functions.scss
djangocms_pai_material_components_web/static/djangocms_pai_material_components_web/node_modules/@material/animation/_variables.scss
djangocms_pai_material_components_web/static/djangocms_pai_material_components_web/node_modules/@material/animation/index.js
djangocms_pai_material_components_web/static/djangocms_pai_material_components_web/node_modules/@material/animation/package.json
djangocms_pai_material_components_web/static/djangocms_pai_material_components_web/node_modules/@material/animation/dist/mdc.animation.js
djangocms_pai_material_components_web/static/djangocms_pai_material_components_web/node_modules/@material/animation/dist/mdc.animation.min.js
djangocms_pai_material_components_web/static/djangocms_pai_material_components_web/node_modules/@material/base/README.md
djangocms_pai_material_components_web/static/djangocms_pai_material_components_web/node_modules/@material/base/_mixins.scss
djangocms_pai_material_components_web/static/djangocms_pai_material_components_web/node_modules/@material/base/component.js
djangocms_pai_material_components_web/static/djangocms_pai_material_components_web/node_modules/@material/base/foundation.js
djangocms_pai_material_components_web/static/djangocms_pai_material_components_web/node_modules/@material/base/index.js
djangocms_pai_material_components_web-0.0.3.dist-info/AUTHORS.rst
djangocms_pai_material_components_web-0.0.3.dist-info/LICENSE.txt
djangocms_pai_material_components_web-0.0.3.dist-info/METADATA
djangocms_pai_material_components_web-0.0.3.dist-info/WHEEL
djangocms_pai_material_components_web-0.0.3.dist-info/top_level.txt
djangocms_pai_material_components_web-0.0.3.dist-info/RECORD
