Metadata-Version: 2.1
Name: djangocms-pai-material-components-web
Version: 0.0.3
Summary: Add a short description here!
Home-page: https://bitbucket.org/pai/djangocms-pai-material-components-web
Author: pai
Author-email: paiuolo@gmail.com
License: mit
Platform: any
Classifier: Development Status :: 4 - Beta
Classifier: Programming Language :: Python
Provides-Extra: testing
Requires-Dist: pytest ; extra == 'testing'
Requires-Dist: pytest-cov ; extra == 'testing'
